setup.py
nbgraph/__init__.py
nbgraph/notebook_graph.py
nbgraph/renderer.py
nbgraph.egg-info/PKG-INFO
nbgraph.egg-info/SOURCES.txt
nbgraph.egg-info/dependency_links.txt
nbgraph.egg-info/requires.txt
nbgraph.egg-info/top_level.txt
nbgraph/client/__init__.py
nbgraph/client/graph.html
nbgraph/client/prepare_notebook.html
nbgraph/client/js/__init__.py
nbgraph/client/js/main.js
nbgraph/client/js/nbgraph.js
nbgraph/client/js/sigma.layout.forceAtlas2.min.js
nbgraph/client/js/sigma.min.js
nbgraph/loaders/__init__.py
nbgraph/loaders/igraph_loader.py
nbgraph/loaders/igraph_loader_test.py
nbgraph/loaders/networkx_loader.py
nbgraph/loaders/networkx_loader_test.py