Metadata-Version: 1.0
Name: nbgraph
Version: 0.0.4
Summary: Interactive graph exploration inside of a Jupyter notebook.
Home-page: https://github.com/paulgb/nbgraph
Author: Paul Butler
Author-email: paulgb@gmail.com
License: MIT
Platform: UNKNOWN
